KSockets/__init__.py
KSockets/connectionless.py
KSockets/constants.py
KSockets/exceptions.py
KSockets/multiplexor.py
KSockets/options.py
KSockets/packers.py
KSockets/secure.py
KSockets/simplesocket.py
KSockets/socket_api.py
KSockets/tools.py
KSockets/version.py
KSockets-1.0.1.dist-info/METADATA
KSockets-1.0.1.dist-info/WHEEL
KSockets-1.0.1.dist-info/top_level.txt
KSockets-1.0.1.dist-info/RECORD
