Metadata-Version: 2.1
Name: KSockets
Version: 1.0.1
Summary: A very simple python sockets
Author-email: Milbert Jr Macarambon <support@kinuseka.us>
Project-URL: homepage, https://gitlab.com/mcaffeine/SimpleSocket
Keywords: python,sockets,networking,communication
Classifier: Programming Language :: Python :: 3.10
Classifier: Operating System :: OS Independent
Classifier: Operating System :: Microsoft :: Windows
Classifier: Operating System :: POSIX :: Linux
Classifier: Operating System :: MacOS
Classifier: Intended Audience :: Developers
Classifier: Typing :: Typed
Requires-Python: >=3.8
Requires-Dist: loguru>=0.7.2
Requires-Dist: semver<4,>=3
